pandiet/__init__.py
pandiet/core.py
tests/__init__.py
tests/test_core.py
pandiet-0.1.9.dist-info/LICENSE
pandiet-0.1.9.dist-info/METADATA
pandiet-0.1.9.dist-info/WHEEL
pandiet-0.1.9.dist-info/top_level.txt
pandiet-0.1.9.dist-info/RECORD
